Metadata-Version: 2.1
Name: tkint3r
Version: 1.0.2
Summary: by billythegoat356, loTus01 and BlueRed
Author-email: <billythegoat356@gmail.com>
License: Eclipse Public License 2.0
Keywords: cli,fade,colors,terminal,tui
